[
  {
    "modality": "yoga",
    "count": 28,
    "pctOfAllNew": 33.3,
    "pctOfModality": 7
  },
  {
    "modality": "pilates",
    "count": 25,
    "pctOfAllNew": 29.8,
    "pctOfModality": 11
  },
  {
    "modality": "strength-training",
    "count": 21,
    "pctOfAllNew": 25,
    "pctOfModality": 11.2
  },
  {
    "modality": "boxing",
    "count": 17,
    "pctOfAllNew": 20.2,
    "pctOfModality": 9.2
  },
  {
    "modality": "reformer-pilates",
    "count": 10,
    "pctOfAllNew": 11.9,
    "pctOfModality": 12.3
  },
  {
    "modality": "cycling",
    "count": 6,
    "pctOfAllNew": 7.1,
    "pctOfModality": 15.4
  },
  {
    "modality": "aerial",
    "count": 5,
    "pctOfAllNew": 6,
    "pctOfModality": 10.9
  },
  {
    "modality": "barre",
    "count": 5,
    "pctOfAllNew": 6,
    "pctOfModality": 5.6
  },
  {
    "modality": "stretching",
    "count": 5,
    "pctOfAllNew": 6,
    "pctOfModality": 19.2
  },
  {
    "modality": "outdoors",
    "count": 3,
    "pctOfAllNew": 3.6,
    "pctOfModality": 5.3
  }
]